rosBNO055.py
ros_inertial_measurement_unit.py
ros_safe_inertial_measurement_unit.py
imu4gopigo3ros-0.6.data/scripts/calibrateIMU
imu4gopigo3ros-0.6.data/scripts/logIMU
imu4gopigo3ros-0.6.data/scripts/readIMU
imu4gopigo3ros-0.6.data/scripts/resetIMU
imu4gopigo3ros-0.6.data/scripts/startIMU
imu4gopigo3ros-0.6.dist-info/LICENSE
imu4gopigo3ros-0.6.dist-info/METADATA
imu4gopigo3ros-0.6.dist-info/WHEEL
imu4gopigo3ros-0.6.dist-info/top_level.txt
imu4gopigo3ros-0.6.dist-info/RECORD
